odoo/addons/footer_extra_info_base/README.rst
odoo/addons/footer_extra_info_base/__init__.py
odoo/addons/footer_extra_info_base/__manifest__.py
odoo/addons/footer_extra_info_base/models/__init__.py
odoo/addons/footer_extra_info_base/models/footer_extra_info_mixin.py
odoo/addons/footer_extra_info_base/readme/CONFIGURE.md
odoo/addons/footer_extra_info_base/readme/CONTRIBUTORS.md
odoo/addons/footer_extra_info_base/readme/DESCRIPTION.md
odoo/addons/footer_extra_info_base/static/description/icon.png
odoo/addons/footer_extra_info_base/static/description/index.html
odoo/addons/footer_extra_info_base/views/report_templates.xml
odoo_addon_footer_extra_info_base-16.0.1.0.0.dist-info/METADATA
odoo_addon_footer_extra_info_base-16.0.1.0.0.dist-info/WHEEL
odoo_addon_footer_extra_info_base-16.0.1.0.0.dist-info/top_level.txt
odoo_addon_footer_extra_info_base-16.0.1.0.0.dist-info/RECORD
